{"chunk_definitions":[{"row":9,"row_count":1,"visible":true,"expansion_state":0,"options":{"engine":"r","label":"setup","include":false},"document_id":"FF6384E3","chunk_id":"csetup_chunk","chunk_label":"setup"},{"row":50,"row_count":1,"visible":true,"expansion_state":0,"options":{"engine":"r","label":"unnamed-chunk-1"},"document_id":"FF6384E3","chunk_id":"cab3rz1981ieb","chunk_label":"unnamed-chunk-1"},{"row":70,"row_count":1,"visible":true,"expansion_state":0,"options":{"engine":"r","label":"unnamed-chunk-3"},"document_id":"FF6384E3","chunk_id":"crxhmwypqcw3o","chunk_label":"unnamed-chunk-2"},{"row":104,"row_count":1,"visible":true,"expansion_state":0,"options":{"engine":"r","label":"unnamed-chunk-2"},"document_id":"FF6384E3","chunk_id":"c4hx38277vb23","chunk_label":"unnamed-chunk-3"}],"doc_write_time":1636595285,"working_dir":null,"default_chunk_options":{"echo":true,"message":false,"warning":false}}